{
  "strata": [
    { "id": 1, "name": "表土层", "color": "#d2b48c", "depthTop": 0, "depthBottom": 0.8, "period": "现代" },
    { "id": 2, "name": "耕作层", "color": "#cd853f", "depthTop": 0.8, "depthBottom": 2.0, "period": "唐宋" },
    { "id": 3, "name": "文化层A", "color": "#deb887", "depthTop": 2.0, "depthBottom": 3.8, "period": "汉魏晋" },
    { "id": 4, "name": "文化层B", "color": "#d2691e", "depthTop": 3.8, "depthBottom": 6.0, "period": "战国秦汉" },
    { "id": 5, "name": "文化层C", "color": "#8b4513", "depthTop": 6.0, "depthBottom": 8.5, "period": "西周春秋" },
    { "id": 6, "name": "基岩层", "color": "#4a2c2a", "depthTop": 8.5, "depthBottom": 12.0, "period": "史前" }
  ],
  "artifacts": [
    { "id": "T001", "name": "青瓷莲花尊", "year": 1400, "material": "青瓷", "description": "北朝时期青瓷莲花尊，器身饰多层仰覆莲瓣，釉色青中泛黄，是北方青瓷的代表性器物。", "stratumId": 3, "position": { "x": 2.1, "y": 2.8, "z": -1.4 }, "category": "陶器" },
    { "id": "T002", "name": "白瓷罐", "year": 1100, "material": "白瓷", "description": "北宋定窑系白瓷罐，器形饱满，胎质洁白坚致，釉色匀净光润，是北方白瓷的上乘之作。", "stratumId": 2, "position": { "x": -3.2, "y": 1.4, "z": 2.3 }, "category": "陶器" },
    { "id": "T003", "name": "开元通宝", "year": 1300, "material": "铜", "description": "唐代开元通宝钱，钱文端庄秀丽，由欧阳询书写，是唐代流通最广的货币。", "stratumId": 3, "position": { "x": 0.7, "y": 2.9, "z": 0.9 }, "category": "青铜器" },
    { "id": "T004", "name": "三彩马俑残件", "year": 1300, "material": "陶釉", "description": "唐代三彩马俑残件，施黄、绿、白三色彩釉，马身肥硕矫健，体现盛唐气象。", "stratumId": 3, "position": { "x": 1.3, "y": 3.2, "z": 3.1 }, "category": "陶器" },
    { "id": "T005", "name": "银碗", "year": 1200, "material": "银", "description": "唐代银质茶碗，内壁光素，外壁錾刻缠枝花草纹，是唐代金银器制作工艺的实物见证。", "stratumId": 3, "position": { "x": -2.6, "y": 2.5, "z": -3.6 }, "category": "青铜器" },
    { "id": "T006", "name": "玉带銙", "year": 1100, "material": "和田玉", "description": "北宋玉带銙，玉质温润呈青白色，正面剔刻胡人乐舞纹，是宋代玉带制度的实物。", "stratumId": 2, "position": { "x": 3.8, "y": 1.7, "z": -2.9 }, "category": "玉器" },
    { "id": "T007", "name": "影青釉注碗", "year": 900, "material": "青白瓷", "description": "北宋景德镇窑影青釉注子温碗一套，通体施青白釉，釉色晶莹如青玉。", "stratumId": 2, "position": { "x": -0.9, "y": 1.6, "z": 4.0 }, "category": "陶器" },
    { "id": "T008", "name": "铜钱一组", "year": 950, "material": "铜", "description": "北宋咸平元宝铜钱18枚，钱文真书旋读，铸工精整，对研究北宋早期货币流通有价值。", "stratumId": 2, "position": { "x": 2.0, "y": 1.3, "z": 0.5 }, "category": "青铜器" },
    { "id": "T009", "name": "黑釉茶盏", "year": 850, "material": "黑瓷", "description": "南宋建窑黑釉兔毫盏，釉面密布银灰色兔毫纹，是宋代斗茶风尚的专用器具。", "stratumId": 2, "position": { "x": -4.0, "y": 1.9, "z": -1.0 }, "category": "陶器" },
    { "id": "T010", "name": "漆奁残片", "year": 1000, "material": "漆木", "description": "宋代漆奁残片，木胎髹黑漆，表面可见螺钿镶嵌痕迹，虽残犹珍。", "stratumId": 2, "position": { "x": 0.3, "y": 1.5, "z": -4.1 }, "category": "骨器" },
    { "id": "T011", "name": "陶磨", "year": 1800, "material": "陶", "description": "东汉陶磨模型，上下两扇，刻有磨齿纹，是研究汉代粮食加工工具的明器。", "stratumId": 4, "position": { "x": 3.5, "y": 4.9, "z": 1.6 }, "category": "陶器" },
    { "id": "T012", "name": "五铢钱范", "year": 2000, "material": "陶", "description": "西汉五铢钱陶范，范面整齐排列12枚五铢钱模，对研究汉代铸钱工艺意义重大。", "stratumId": 4, "position": { "x": -1.1, "y": 5.2, "z": -2.4 }, "category": "陶器" },
    { "id": "T013", "name": "铁剑", "year": 1900, "material": "铁", "description": "西汉铁长剑，剑身狭长，虽经锈蚀仍可辨其原有形制，是汉代兵器的重要实物。", "stratumId": 4, "position": { "x": -3.7, "y": 5.7, "z": 0.6 }, "category": "青铜器" },
    { "id": "T014", "name": "玉璜", "year": 2100, "material": "青玉", "description": "战国青玉璜，扇面形，两端雕刻龙首，通体光素无纹，是战国组佩构件之一。", "stratumId": 4, "position": { "x": 0.5, "y": 5.0, "z": 3.8 }, "category": "玉器" },
    { "id": "T015", "name": "半两钱", "year": 2200, "material": "铜", "description": "秦代半两钱，钱文篆书，字形狭长，制作较规整，是秦代统一货币的实物遗存。", "stratumId": 4, "position": { "x": 2.7, "y": 4.5, "z": -3.7 }, "category": "青铜器" },
    { "id": "T016", "name": "茧形壶", "year": 2100, "material": "陶", "description": "西汉灰陶茧形壶，器身呈横椭圆茧形，肩部刻划弦纹，是秦末汉初典型器形。", "stratumId": 4, "position": { "x": 4.1, "y": 5.4, "z": 2.9 }, "category": "陶器" },
    { "id": "T017", "name": "铜鼎残耳", "year": 2400, "material": "青铜", "description": "战国青铜鼎残耳，饰蟠螭纹，铸工精细，可推知原鼎形体硕大，工艺考究。", "stratumId": 5, "position": { "x": -2.2, "y": 7.5, "z": 1.3 }, "category": "青铜器" },
    { "id": "T018", "name": "陶豆", "year": 2600, "material": "陶", "description": "春秋晚期陶豆，盘深腹圆，柄部较高，施黑衣陶衣，是春秋时期礼器组合的一员。", "stratumId": 5, "position": { "x": 1.8, "y": 7.1, "z": -1.9 }, "category": "陶器" },
    { "id": "T019", "name": "骨贝", "year": 2700, "material": "骨", "description": "西周早期骨贝，仿海贝磨制而成，背部穿孔，是商周时期的代用货币。", "stratumId": 5, "position": { "x": 0.1, "y": 7.9, "z": 3.4 }, "category": "骨器" },
    { "id": "T020", "name": "原始青瓷豆", "year": 2800, "material": "原始瓷", "description": "西周原始青瓷豆，釉色青黄不均，胎釉结合稍差，是瓷器处于原始阶段的见证。", "stratumId": 5, "position": { "x": -4.3, "y": 7.3, "z": -0.7 }, "category": "陶器" },
    { "id": "T021", "name": "青瓷虎子", "year": 1600, "material": "青瓷", "description": "东晋越窑青瓷虎子，作伏虎形，张口昂首，釉色青润，是魏晋青瓷精品。", "stratumId": 3, "position": { "x": -1.5, "y": 3.0, "z": -2.7 }, "category": "陶器" },
    { "id": "T022", "name": "铜弩机", "year": 1750, "material": "青铜", "description": "东汉铜弩机，构件保存基本完整，有望山、悬刀、钩心，是汉代远射兵器的核心部件。", "stratumId": 4, "position": { "x": 3.9, "y": 5.1, "z": 0.2 }, "category": "青铜器" },
    { "id": "T023", "name": "绿釉陶壶", "year": 1850, "material": "陶釉", "description": "东汉低温铅绿釉陶壶，肩部贴塑铺首，通体施翠绿釉，有银绿色返铅光泽。", "stratumId": 4, "position": { "x": -0.3, "y": 4.7, "z": 1.5 }, "category": "陶器" },
    { "id": "T024", "name": "玉握猪", "year": 1800, "material": "白玉", "description": "西汉白玉握猪一对，造型简洁洗练，仅用数道阴线刻出轮廓，是典型的'汉八刀'。", "stratumId": 4, "position": { "x": 1.6, "y": 5.5, "z": -3.2 }, "category": "玉器" },
    { "id": "T025", "name": "彩绘陶奁", "year": 1950, "material": "陶", "description": "西汉彩绘云气纹陶奁，直壁平底，器身以朱、墨、绿彩绘云气瑞兽纹，色彩绚丽。", "stratumId": 4, "position": { "x": -3.0, "y": 4.4, "z": 3.5 }, "category": "陶器" },
    { "id": "T026", "name": "铜带钩", "year": 2300, "material": "青铜", "description": "战国错金银铜带钩，钩身修长，以金银丝错出卷云纹，华丽精致，为贵族服饰用具。", "stratumId": 5, "position": { "x": 2.4, "y": 6.9, "z": 2.0 }, "category": "青铜器" },
    { "id": "T027", "name": "印纹硬陶罐", "year": 2500, "material": "陶", "description": "春秋印纹硬陶罐，器身拍印米字纹，胎质坚硬致密，是南方吴越文化典型器物。", "stratumId": 5, "position": { "x": -1.8, "y": 7.7, "z": -3.9 }, "category": "陶器" },
    { "id": "T028", "name": "卜甲残片", "year": 2900, "material": "骨", "description": "西周早期卜甲残片，背面有整齐的方形钻凿，正面可见灼裂兆纹，是周人占卜的实物。", "stratumId": 5, "position": { "x": 3.7, "y": 8.0, "z": -2.5 }, "category": "骨器" },
    { "id": "T029", "name": "铜铃", "year": 2950, "material": "青铜", "description": "西周早期青铜铃，器身合瓦形，半环形钮，腔内有铃舌残迹，是周代礼乐用器。", "stratumId": 5, "position": { "x": -0.6, "y": 7.0, "z": 0.3 }, "category": "青铜器" },
    { "id": "T030", "name": "玉鸟形饰", "year": 3000, "material": "青玉", "description": "西周青玉鸟形饰，以夸张手法雕琢昂首翘尾之鸟形，线刻简练有力，是周代玉佩饰件。", "stratumId": 5, "position": { "x": 4.2, "y": 6.7, "z": 3.3 }, "category": "玉器" },
    { "id": "T031", "name": "黄釉瓷碗", "year": 1500, "material": "瓷", "description": "北齐相州窑黄釉瓷碗，器形敦厚，釉色深黄匀净，开细碎片纹，是北方早期瓷器。", "stratumId": 3, "position": { "x": 0.9, "y": 3.5, "z": 1.1 }, "category": "陶器" },
    { "id": "T032", "name": "褐釉鸡首壶", "year": 1650, "material": "瓷", "description": "东晋德清窑褐釉鸡首壶，鸡首高昂，施深褐釉，釉不及底，是德清窑的典型产品。", "stratumId": 3, "position": { "x": -2.4, "y": 2.9, "z": 3.6 }, "category": "陶器" },
    { "id": "T033", "name": "鎏金铜铺首", "year": 1700, "material": "铜鎏金", "description": "西晋鎏金铜铺首，作兽面衔环状，通体鎏金，金光灿然，原当装饰于大型漆木器。", "stratumId": 4, "position": { "x": 3.0, "y": 4.2, "z": -0.8 }, "category": "青铜器" },
    { "id": "T034", "name": "陶猪圈模型", "year": 1750, "material": "陶", "description": "东汉陶猪圈模型，方形围栏，内有陶猪一头，旁附厕所，是反映汉代庄园经济的明器。", "stratumId": 4, "position": { "x": -4.1, "y": 5.0, "z": -1.5 }, "category": "陶器" },
    { "id": "T035", "name": "石砚", "year": 1550, "material": "石材", "description": "南北朝青石砚，箕斗形，砚面研磨区光滑，池部深凹，是南北朝文房用具的代表。", "stratumId": 3, "position": { "x": 2.6, "y": 3.2, "z": -3.8 }, "category": "石器" },
    { "id": "T036", "name": "金指环", "year": 1450, "material": "金", "description": "隋代金指环，环身光素，一端镶嵌蓝色料珠，虽简而华贵，是隋代金首饰实物。", "stratumId": 3, "position": { "x": -1.0, "y": 3.6, "z": -0.4 }, "category": "玉器" },
    { "id": "T037", "name": "彩绘陶马", "year": 1400, "material": "陶", "description": "隋代彩绘陶马，形体高大矫健，施以红、黑、白彩，造型精准，开唐三彩之先河。", "stratumId": 3, "position": { "x": 1.1, "y": 3.8, "z": 3.9 }, "category": "陶器" },
    { "id": "T038", "name": "青瓷八系罐", "year": 1450, "material": "瓷", "description": "隋代越窑青瓷八系罐，肩部设四桥系四复系，施青釉微泛黄色，为隋代青瓷典型。", "stratumId": 3, "position": { "x": 3.4, "y": 2.7, "z": 2.7 }, "category": "陶器" },
    { "id": "T039", "name": "铁釜", "year": 1100, "material": "铁", "description": "北宋铸铁釜，敛口圆底，厚重坚实，是宋代民间炊具的主要形制。", "stratumId": 2, "position": { "x": -3.5, "y": 1.8, "z": 1.8 }, "category": "青铜器" },
    { "id": "T040", "name": "酱釉瓷罐", "year": 1050, "material": "瓷", "description": "北宋当阳峪窑酱釉罐，釉色酱红莹润，器形端庄，是北方民间窑场的产品。", "stratumId": 2, "position": { "x": 0.4, "y": 1.5, "z": -2.1 }, "category": "陶器" },
    { "id": "T041", "name": "素面铜镜", "year": 1150, "material": "青铜", "description": "北宋素面铜镜，圆形，窄缘，桥形钮，无纹饰，是宋代大量使用的普通铜镜。", "stratumId": 2, "position": { "x": -0.2, "y": 1.2, "z": 2.2 }, "category": "青铜器" },
    { "id": "T042", "name": "青白瓷粉盒", "year": 950, "material": "瓷", "description": "南宋景德镇窑青白瓷粉盒，盖面划刻折枝花卉，子母口扣合紧密，是妇女妆奁用具。", "stratumId": 2, "position": { "x": 4.0, "y": 1.6, "z": 1.0 }, "category": "陶器" },
    { "id": "T043", "name": "铜钱牌", "year": 900, "material": "铜", "description": "南宋钱牌，长方形，上端有穿孔，两面钱文，是南宋末年通货膨胀的产物。", "stratumId": 2, "position": { "x": -2.8, "y": 1.4, "z": -3.3 }, "category": "青铜器" },
    { "id": "T044", "name": "玉璧", "year": 2600, "material": "青玉", "description": "春秋青玉璧，玉质有天然石纹，璧面光素，边缘规整，是春秋时期祭祀用玉。", "stratumId": 5, "position": { "x": 0.8, "y": 6.5, "z": -3.5 }, "category": "玉器" },
    { "id": "T045", "name": "原始瓷盂", "year": 2850, "material": "原始瓷", "description": "西周原始青瓷盂，器形小巧，青黄釉厚薄不匀，是原始瓷器的早期形态。", "stratumId": 5, "position": { "x": -3.6, "y": 7.6, "z": 2.6 }, "category": "陶器" },
    { "id": "T046", "name": "铜削", "year": 2750, "material": "青铜", "description": "西周青铜削刀，环首直柄，刀刃锋利，是周代常用的小型工具，用于刮削竹木简。", "stratumId": 5, "position": { "x": 2.9, "y": 7.3, "z": 0.7 }, "category": "青铜器" },
    { "id": "T047", "name": "骨笄", "year": 2900, "material": "骨", "description": "西周骨笄一组三支，首部雕琢成鸟首形，通体磨光，是周代贵族妇女束发用具。", "stratumId": 5, "position": { "x": -1.4, "y": 8.1, "z": -1.7 }, "category": "骨器" },
    { "id": "T048", "name": "玛瑙珠", "year": 2500, "material": "玛瑙", "description": "春秋红玛瑙管珠，颜色深红，两端平切，中有穿孔，是当时贵族组佩中的串饰。", "stratumId": 5, "position": { "x": 1.4, "y": 7.8, "z": 3.0 }, "category": "玉器" },
    { "id": "T049", "name": "铜车軎", "year": 2250, "material": "青铜", "description": "战国青铜车軎一对，圆筒形，外壁饰蟠螭纹，是古代车轴两端的固定部件。", "stratumId": 5, "position": { "x": -4.4, "y": 6.8, "z": -3.1 }, "category": "青铜器" },
    { "id": "T050", "name": "陶鼎", "year": 2400, "material": "陶", "description": "战国仿铜陶鼎，子母口盖，三兽蹄足，腹饰弦纹，是战国墓中常见的仿铜陶礼器。", "stratumId": 5, "position": { "x": 3.3, "y": 7.0, "z": -4.0 }, "category": "陶器" },
    { "id": "T051", "name": "白瓷执壶", "year": 1100, "material": "白瓷", "description": "北宋定窑系白瓷执壶，瓜棱形腹，细长流，釉色白中闪青，为北宋日常酒器。", "stratumId": 2, "position": { "x": 1.9, "y": 1.7, "z": -1.2 }, "category": "陶器" },
    { "id": "T052", "name": "绞胎瓷枕", "year": 1200, "material": "瓷", "description": "唐代巩县窑绞胎瓷枕，以褐白两色瓷土绞揉出木理纹，工艺独特，极为珍稀。", "stratumId": 3, "position": { "x": -2.1, "y": 3.3, "z": 1.4 }, "category": "陶器" },
    { "id": "T053", "name": "葡萄纹铜镜", "year": 1350, "material": "青铜", "description": "唐代瑞兽葡萄纹铜镜，圆形，海兽葡萄纹饰繁缛，是盛唐铜镜的杰出代表。", "stratumId": 3, "position": { "x": 2.8, "y": 2.8, "z": -2.5 }, "category": "青铜器" },
    { "id": "T054", "name": "莲花纹地砖", "year": 1400, "material": "陶", "description": "唐代莲花纹方砖，模印宝相莲花纹，纹饰饱满华丽，是宫殿建筑的铺装材料。", "stratumId": 3, "position": { "x": 0.2, "y": 3.6, "z": 3.7 }, "category": "陶器" },
    { "id": "T055", "name": "三彩塔式罐", "year": 1300, "material": "陶釉", "description": "唐代三彩塔式罐，由盖、罐、座三部分组成，施黄、绿、蓝三彩，是丧葬专用明器。", "stratumId": 3, "position": { "x": -3.9, "y": 3.5, "z": -2.9 }, "category": "陶器" },
    { "id": "T056", "name": "银盒", "year": 1250, "material": "银", "description": "唐代银鎏金小盒，盒面锤揲鸳鸯莲池纹，工艺精湛，原当盛放化妆品或香料。", "stratumId": 3, "position": { "x": 4.4, "y": 2.6, "z": 0.4 }, "category": "青铜器" },
    { "id": "T057", "name": "陶碓", "year": 1800, "material": "陶", "description": "东汉陶碓模型，杵、臼、支架俱全，是研究汉代粮食加工机械的重要实物。", "stratumId": 4, "position": { "x": -0.7, "y": 5.3, "z": 2.7 }, "category": "陶器" },
    { "id": "T058", "name": "红陶灶", "year": 1900, "material": "陶", "description": "西汉红陶灶，船形，灶面开三个火眼，上置甑、釜、罐等炊具，是汉代明器灶的典型。", "stratumId": 4, "position": { "x": 2.3, "y": 4.9, "z": -3.0 }, "category": "陶器" },
    { "id": "T059", "name": "铜博山炉", "year": 2000, "material": "青铜", "description": "西汉青铜博山炉，炉盖作层叠山峦形，山峦间有仙人瑞兽，是汉代焚香用器。", "stratumId": 4, "position": { "x": -2.9, "y": 5.5, "z": 0.1 }, "category": "青铜器" },
    { "id": "T060", "name": "玉翁仲", "year": 2050, "material": "白玉", "description": "西汉玉翁仲，以圆雕手法刻一文官立像，造型极简，是汉代流行的辟邪佩饰。", "stratumId": 4, "position": { "x": 3.1, "y": 5.8, "z": 3.2 }, "category": "玉器" },
    { "id": "T061", "name": "陶仓", "year": 1950, "material": "陶", "description": "西汉釉陶仓，圆筒形，三熊足，肩有三道弦纹，是汉代庄园储粮的明器模型。", "stratumId": 4, "position": { "x": -4.2, "y": 4.6, "z": -3.4 }, "category": "陶器" },
    { "id": "T062", "name": "铜戈", "year": 2550, "material": "青铜", "description": "春秋早期青铜戈，援部上扬，胡部有三穿，内尾上翘，是春秋车战的主要兵器。", "stratumId": 5, "position": { "x": 0.6, "y": 7.4, "z": -0.2 }, "category": "青铜器" },
    { "id": "T063", "name": "陶鬲", "year": 2700, "material": "陶", "description": "西周晚期陶鬲，三袋足，肩部绳纹，器形厚重，是周代最主要的炊器。", "stratumId": 5, "position": { "x": -1.7, "y": 7.9, "z": 2.1 }, "category": "陶器" },
    { "id": "T064", "name": "铜簋耳", "year": 2800, "material": "青铜", "description": "西周青铜簋兽首耳残件，以圆雕手法铸出兽首，角、目、鼻清晰，工艺精湛。", "stratumId": 5, "position": { "x": 3.6, "y": 7.2, "z": -1.8 }, "category": "青铜器" },
    { "id": "T065", "name": "石圭", "year": 2850, "material": "石材", "description": "西周石圭，尖首长条形，磨制光滑，是周代举行朝聘、祭祀时使用的礼器。", "stratumId": 5, "position": { "x": -3.3, "y": 6.9, "z": -4.2 }, "category": "石器" },
    { "id": "T066", "name": "青瓷四系罐", "year": 1700, "material": "瓷", "description": "西晋越窑青瓷四系罐，肩部设四横系，器身印网格带纹，青釉莹润匀净。", "stratumId": 4, "position": { "x": 1.0, "y": 4.2, "z": 0.9 }, "category": "陶器" },
    { "id": "T067", "name": "青瓷唾壶", "year": 1550, "material": "瓷", "description": "南朝越窑青瓷唾壶，盘口细颈，扁圆腹，施青釉，是贵族居室内的卫生用具。", "stratumId": 3, "position": { "x": -2.7, "y": 3.4, "z": -0.6 }, "category": "陶器" },
    { "id": "T068", "name": "铜灯", "year": 2100, "material": "青铜", "description": "秦代铜灯，豆形灯盘，柱形柄，喇叭形圈足，结构简洁实用，是秦代日用铜器。", "stratumId": 4, "position": { "x": 2.5, "y": 4.7, "z": 2.4 }, "category": "青铜器" },
    { "id": "T069", "name": "陶井", "year": 1850, "material": "陶", "description": "东汉陶井模型，方形井栏，上设井架及滑轮，旁有水罐，是汉代生活设施的缩影。", "stratumId": 4, "position": { "x": -0.5, "y": 5.0, "z": -2.8 }, "category": "陶器" },
    { "id": "T070", "name": "铜印章", "year": 2150, "material": "青铜", "description": "战国铜私玺，桥形钮，印面方形，铸阴文四字，为当时贵族官吏的身份凭信。", "stratumId": 5, "position": { "x": 4.0, "y": 6.6, "z": 1.7 }, "category": "青铜器" },
    { "id": "T071", "name": "青瓷熏炉", "year": 1600, "material": "瓷", "description": "南朝青瓷博山熏炉，炉盖堆塑山峰，山峰间镂雕出烟孔，工艺精巧。", "stratumId": 3, "position": { "x": -3.8, "y": 3.1, "z": 3.9 }, "category": "陶器" },
    { "id": "T072", "name": "彩绘陶俑", "year": 2000, "material": "陶", "description": "西汉彩绘陶侍女俑，面庞圆润，眉目清秀，身着三重深衣，色彩尚存，是西汉陶俑精品。", "stratumId": 4, "position": { "x": 0.0, "y": 5.6, "z": 3.6 }, "category": "陶器" },
    { "id": "T073", "name": "铜量器", "year": 2250, "material": "青铜", "description": "战国铜方升，直口方壁，平底，器壁外侧有刻度，是战国时期的标准量器。", "stratumId": 5, "position": { "x": -2.5, "y": 6.8, "z": 0.8 }, "category": "青铜器" },
    { "id": "T074", "name": "陶匜", "year": 2600, "material": "陶", "description": "春秋陶匜，仿青铜匜形，前有长流，后有鋬，是沃盥之礼的注水器。", "stratumId": 5, "position": { "x": 2.0, "y": 7.5, "z": 2.5 }, "category": "陶器" },
    { "id": "T075", "name": "铜矛", "year": 2650, "material": "青铜", "description": "春秋晚期青铜矛，柳叶形矛叶，中脊起棱，矛骹两侧有系环，是步兵常用刺兵。", "stratumId": 5, "position": { "x": -1.2, "y": 7.1, "z": -3.6 }, "category": "青铜器" },
    { "id": "T076", "name": "白瓷碗", "year": 1300, "material": "白瓷", "description": "唐代邢窑白瓷碗，玉璧形底，胎质坚硬细腻，釉色纯白如银，是邢窑的典型器物。", "stratumId": 3, "position": { "x": 3.7, "y": 3.0, "z": 3.4 }, "category": "陶器" },
    { "id": "T077", "name": "花釉瓷拍鼓", "year": 1250, "material": "瓷", "description": "唐代鲁山窑花釉瓷拍鼓，黑釉上泼洒灰蓝色彩斑，是唐代陶瓷与音乐结合的珍贵实物。", "stratumId": 3, "position": { "x": -0.4, "y": 3.4, "z": -3.9 }, "category": "陶器" },
    { "id": "T078", "name": "秘色瓷碟", "year": 1100, "material": "瓷", "description": "五代越窑秘色瓷碟，釉色青绿如湖水，晶莹润泽，是专门供奉皇室的越窑精品。", "stratumId": 2, "position": { "x": -3.4, "y": 1.9, "z": -0.9 }, "category": "陶器" },
    { "id": "T079", "name": "铜钹", "year": 1000, "material": "青铜", "description": "北宋铜钹一对，圆形，中部隆起成半球形，是寺院法会常用的打击乐器。", "stratumId": 2, "position": { "x": 1.5, "y": 1.6, "z": 3.8 }, "category": "青铜器" },
    { "id": "T080", "name": "定窑白瓷枕", "year": 950, "material": "白瓷", "description": "北宋定窑白瓷孩儿枕，作童子伏卧状，以孩童脊背为枕面，是定窑雕塑瓷的杰作。", "stratumId": 2, "position": { "x": 2.2, "y": 1.5, "z": -3.5 }, "category": "陶器" },
    { "id": "T081", "name": "越窑青瓷灯", "year": 1800, "material": "瓷", "description": "东汉越窑青瓷熊形灯，器身塑成坐熊，熊头顶灯盏，造型生动有趣，是早期青瓷佳作。", "stratumId": 4, "position": { "x": -4.0, "y": 4.8, "z": 2.0 }, "category": "陶器" },
    { "id": "T082", "name": "玉剑首", "year": 2300, "material": "白玉", "description": "战国白玉剑首，圆形，正面减地浮雕谷纹，是镶嵌于剑柄顶端的玉饰件。", "stratumId": 5, "position": { "x": 0.7, "y": 6.7, "z": 1.2 }, "category": "玉器" },
    { "id": "T083", "name": "陶排水管", "year": 200, "material": "陶", "description": "西周陶质水管，圆筒形，一端稍粗呈子母口，可套接使用，是早期城市排水设施的实物。", "stratumId": 5, "position": { "x": -0.9, "y": 7.6, "z": 3.9 }, "category": "陶器" },
    { "id": "T084", "name": "铜权", "year": 2000, "material": "青铜", "description": "西汉铜权，呈半球形，权身铸阳文'重一斤'，是汉代标准衡器的实物证据。", "stratumId": 4, "position": { "x": 3.9, "y": 5.6, "z": -1.0 }, "category": "青铜器" },
    { "id": "T085", "name": "青瓷魂瓶", "year": 1750, "material": "瓷", "description": "三国吴青瓷堆塑罐，罐口以上堆塑多层楼阁、人物、飞鸟，是祈求灵魂升天的丧葬用具。", "stratumId": 4, "position": { "x": 1.1, "y": 4.2, "z": 3.1 }, "category": "陶器" },
    { "id": "T086", "name": "黄褐釉陶罐", "year": 1000, "material": "瓷", "description": "北宋磁州窑系黄褐釉陶罐，器身以白彩绘简化牡丹纹，笔法率意奔放。", "stratumId": 2, "position": { "x": 0.2, "y": 1.4, "z": 1.8 }, "category": "陶器" },
    { "id": "T087", "name": "青瓷鸡笼", "year": 1700, "material": "瓷", "description": "西晋越窑青瓷鸡笼，作卷棚式笼舍，笼内塑鸡两只，是富有生活气息的青瓷明器。", "stratumId": 4, "position": { "x": -3.1, "y": 4.5, "z": -1.1 }, "category": "陶器" },
    { "id": "T088", "name": "陶尊", "year": 1000, "material": "陶", "description": "西夏褐釉剔花瓷尊，肩部剔刻牡丹花纹，线条粗犷，是西夏陶瓷的代表性作品。", "stratumId": 2, "position": { "x": 4.3, "y": 1.8, "z": 4.0 }, "category": "陶器" },
    { "id": "T089", "name": "铜剑首", "year": 2000, "material": "青铜", "description": "西汉铜剑首，圆盘形，正面铸浮雕蟠螭纹，背面嵌绿松石，装饰极为华丽。", "stratumId": 4, "position": { "x": -1.8, "y": 4.8, "z": 0.4 }, "category": "青铜器" },
    { "id": "T090", "name": "白瓷高足杯", "year": 1000, "material": "白瓷", "description": "北宋定窑白瓷高足杯，深腹高足，通体施白釉，是仿金银器造型的陶瓷精品。", "stratumId": 2, "position": { "x": -2.2, "y": 1.2, "z": 3.3 }, "category": "陶器" },
    { "id": "T091", "name": "骨箭头", "year": 2000, "material": "骨", "description": "西汉骨箭镞，三棱形，铤部尖锐，磨制精细，是汉代狩猎或军事活动的用具。", "stratumId": 4, "position": { "x": -0.1, "y": 4.6, "z": -4.0 }, "category": "骨器" },
    { "id": "T092", "name": "原始瓷尊", "year": 3000, "material": "原始瓷", "description": "商代晚期原始瓷大口尊，肩腹部拍印篮纹，胎质较粗，是原始瓷器的初始形态。", "stratumId": 5, "position": { "x": 4.2, "y": 8.0, "z": -2.0 }, "category": "陶器" },
    { "id": "T093", "name": "陶簋", "year": 3000, "material": "陶", "description": "商代晚期陶簋，圆腹圈足，腹部饰绳纹附加堆纹，是商代祭祀宴飨的食器。", "stratumId": 5, "position": { "x": -4.0, "y": 8.2, "z": 1.1 }, "category": "陶器" },
    { "id": "T094", "name": "玉戈", "year": 3000, "material": "青玉", "description": "商代晚期玉戈，仿铜戈形制琢制，援、胡、内俱全，是商代贵族的仪仗用玉。", "stratumId": 5, "position": { "x": 1.5, "y": 8.3, "z": 0.5 }, "category": "玉器" },
    { "id": "T095", "name": "铜爵残件", "year": 3000, "material": "青铜", "description": "商代晚期青铜爵残流部，流口上翘，可见纹饰痕迹，是商代最典型的酒礼器。", "stratumId": 5, "position": { "x": -2.5, "y": 7.8, "z": -2.2 }, "category": "青铜器" },
    { "id": "T096", "name": "白釉梅瓶", "year": 1000, "material": "白瓷", "description": "辽代缸瓦窑白釉梅瓶，小口丰肩，器身挺拔，施白釉不到底，是辽代瓷器精品。", "stratumId": 2, "position": { "x": 3.0, "y": 1.9, "z": 1.4 }, "category": "陶器" },
    { "id": "T097", "name": "珍珠地划花瓶", "year": 1000, "material": "瓷", "description": "北宋登封窑珍珠地划花瓶，灰白胎上以小圆圈密布如珍珠，中划花卉，装饰独特。", "stratumId": 2, "position": { "x": -4.4, "y": 1.6, "z": 4.1 }, "category": "陶器" },
    { "id": "T098", "name": "玳瑁釉茶盏", "year": 1000, "material": "瓷", "description": "南宋吉州窑玳瑁釉茶盏，黑釉与黄釉交融如玳瑁斑纹，是吉州窑独有的装饰工艺。", "stratumId": 2, "position": { "x": 2.8, "y": 1.7, "z": -0.1 }, "category": "陶器" },
    { "id": "T099", "name": "鎏金铜佛", "year": 1500, "material": "铜鎏金", "description": "北魏鎏金铜佛造像，结跏趺坐，着通肩袈裟，背光火焰纹，是北魏佛教艺术的结晶。", "stratumId": 3, "position": { "x": 0.0, "y": 3.0, "z": 0.0 }, "category": "青铜器" },
    { "id": "T100", "name": "青瓷虎子", "year": 1800, "material": "瓷", "description": "东汉越窑青瓷虎子，身体圆硕，背上有提梁，张口作流，是最早的青瓷虎子之一。", "stratumId": 4, "position": { "x": -1.0, "y": 5.5, "z": -0.5 }, "category": "陶器" },
    { "id": "T101", "name": "金箔饰片", "year": 1000, "material": "金", "description": "宋代金箔饰片一组，捶拓极薄的金箔，原当粘贴于漆器或木器表面作装饰。", "stratumId": 2, "position": { "x": 0.5, "y": 1.3, "z": -0.9 }, "category": "玉器" }
  ]
}
